Metadata-Version: 2.1
Name: PycordUtils
Version: 0.0.2
Summary: A Useful Utility Library made to be used with pycord
Home-page: https://github.com/xFGhoul/PycordUtils
Author: Ghoul
License: UNKNOWN
Platform: UNKNOWN
Classifier: Programming Language :: Python :: 3
Classifier: License :: OSI Approved :: MIT License
Classifier: Operating System :: OS Independent
Requires-Python: >= 3.6
Provides-Extra: voice
